{
  "scriptId": "310",
  "url": "file:///home/mateusz/Documents/Projects/strings/src/char_width.ts",
  "functions": [
    {
      "functionName": "",
      "ranges": [{ "startOffset": 0, "endOffset": 6006, "count": 1 }],
      "isBlockCoverage": true
    },
    {
      "functionName": "charWidth",
      "ranges": [
        { "startOffset": 507, "endOffset": 6005, "count": 1701 },
        { "startOffset": 593, "endOffset": 602, "count": 0 },
        { "startOffset": 656, "endOffset": 678, "count": 1403 },
        { "startOffset": 702, "endOffset": 724, "count": 1403 },
        { "startOffset": 748, "endOffset": 770, "count": 1403 },
        { "startOffset": 966, "endOffset": 985, "count": 0 },
        { "startOffset": 1043, "endOffset": 1065, "count": 1403 },
        { "startOffset": 1089, "endOffset": 1111, "count": 1403 },
        { "startOffset": 1135, "endOffset": 1157, "count": 1403 },
        { "startOffset": 1181, "endOffset": 1203, "count": 1403 },
        { "startOffset": 1275, "endOffset": 1297, "count": 1403 },
        { "startOffset": 1321, "endOffset": 1343, "count": 1403 },
        { "startOffset": 1367, "endOffset": 1389, "count": 1403 },
        { "startOffset": 1485, "endOffset": 1507, "count": 1403 },
        { "startOffset": 1531, "endOffset": 1553, "count": 1403 },
        { "startOffset": 1577, "endOffset": 1599, "count": 1403 },
        { "startOffset": 1695, "endOffset": 1717, "count": 1403 },
        { "startOffset": 1837, "endOffset": 1859, "count": 1403 },
        { "startOffset": 1955, "endOffset": 1977, "count": 1403 },
        { "startOffset": 2025, "endOffset": 2047, "count": 1403 },
        { "startOffset": 2119, "endOffset": 2141, "count": 1403 },
        { "startOffset": 2213, "endOffset": 2235, "count": 1403 },
        { "startOffset": 2259, "endOffset": 2281, "count": 1403 },
        { "startOffset": 2305, "endOffset": 2327, "count": 1403 },
        { "startOffset": 2351, "endOffset": 2373, "count": 1403 },
        { "startOffset": 2397, "endOffset": 2419, "count": 1403 },
        { "startOffset": 2420, "endOffset": 2465, "count": 1268 },
        { "startOffset": 2443, "endOffset": 2465, "count": 970 },
        { "startOffset": 2466, "endOffset": 2511, "count": 1268 },
        { "startOffset": 2489, "endOffset": 2511, "count": 970 },
        { "startOffset": 2512, "endOffset": 2557, "count": 1268 },
        { "startOffset": 2535, "endOffset": 2557, "count": 970 },
        { "startOffset": 2558, "endOffset": 2603, "count": 1268 },
        { "startOffset": 2581, "endOffset": 2603, "count": 970 },
        { "startOffset": 2604, "endOffset": 2649, "count": 1268 },
        { "startOffset": 2627, "endOffset": 2649, "count": 970 },
        { "startOffset": 2650, "endOffset": 2695, "count": 1268 },
        { "startOffset": 2673, "endOffset": 2695, "count": 970 },
        { "startOffset": 2696, "endOffset": 2741, "count": 1268 },
        { "startOffset": 2719, "endOffset": 2741, "count": 970 },
        { "startOffset": 2742, "endOffset": 2787, "count": 1268 },
        { "startOffset": 2765, "endOffset": 2787, "count": 970 },
        { "startOffset": 2788, "endOffset": 2833, "count": 1236 },
        { "startOffset": 2811, "endOffset": 2833, "count": 938 },
        { "startOffset": 2834, "endOffset": 2879, "count": 1236 },
        { "startOffset": 2857, "endOffset": 2879, "count": 938 },
        { "startOffset": 2880, "endOffset": 2925, "count": 1236 },
        { "startOffset": 2903, "endOffset": 2925, "count": 938 },
        { "startOffset": 2926, "endOffset": 2971, "count": 1148 },
        { "startOffset": 2949, "endOffset": 2971, "count": 850 },
        { "startOffset": 2972, "endOffset": 3017, "count": 1148 },
        { "startOffset": 2995, "endOffset": 3017, "count": 850 },
        { "startOffset": 3018, "endOffset": 3063, "count": 1148 },
        { "startOffset": 3041, "endOffset": 3063, "count": 850 },
        { "startOffset": 3064, "endOffset": 3109, "count": 1148 },
        { "startOffset": 3087, "endOffset": 3109, "count": 850 },
        { "startOffset": 3110, "endOffset": 3155, "count": 1148 },
        { "startOffset": 3133, "endOffset": 3155, "count": 850 },
        { "startOffset": 3156, "endOffset": 3201, "count": 1148 },
        { "startOffset": 3179, "endOffset": 3201, "count": 850 },
        { "startOffset": 3202, "endOffset": 3247, "count": 798 },
        { "startOffset": 3225, "endOffset": 3247, "count": 326 },
        { "startOffset": 3248, "endOffset": 3295, "count": 798 },
        { "startOffset": 3272, "endOffset": 3295, "count": 326 },
        { "startOffset": 3296, "endOffset": 3343, "count": 798 },
        { "startOffset": 3320, "endOffset": 3343, "count": 326 },
        { "startOffset": 3344, "endOffset": 3391, "count": 798 },
        { "startOffset": 3368, "endOffset": 3391, "count": 326 },
        { "startOffset": 3392, "endOffset": 3439, "count": 798 },
        { "startOffset": 3416, "endOffset": 3439, "count": 326 },
        { "startOffset": 3440, "endOffset": 3487, "count": 798 },
        { "startOffset": 3464, "endOffset": 3487, "count": 326 },
        { "startOffset": 3488, "endOffset": 3535, "count": 798 },
        { "startOffset": 3512, "endOffset": 3535, "count": 326 },
        { "startOffset": 3536, "endOffset": 3583, "count": 798 },
        { "startOffset": 3560, "endOffset": 3583, "count": 326 },
        { "startOffset": 3584, "endOffset": 3631, "count": 798 },
        { "startOffset": 3608, "endOffset": 3631, "count": 326 },
        { "startOffset": 3632, "endOffset": 3679, "count": 798 },
        { "startOffset": 3656, "endOffset": 3679, "count": 326 },
        { "startOffset": 3680, "endOffset": 3704, "count": 798 },
        { "startOffset": 3705, "endOffset": 3752, "count": 798 },
        { "startOffset": 3729, "endOffset": 3752, "count": 326 },
        { "startOffset": 3753, "endOffset": 3777, "count": 798 },
        { "startOffset": 3778, "endOffset": 3825, "count": 798 },
        { "startOffset": 3802, "endOffset": 3825, "count": 326 },
        { "startOffset": 3826, "endOffset": 3873, "count": 798 },
        { "startOffset": 3850, "endOffset": 3873, "count": 326 },
        { "startOffset": 3874, "endOffset": 3898, "count": 798 },
        { "startOffset": 3899, "endOffset": 3923, "count": 798 },
        { "startOffset": 3924, "endOffset": 3948, "count": 798 },
        { "startOffset": 3949, "endOffset": 3996, "count": 798 },
        { "startOffset": 3973, "endOffset": 3996, "count": 326 },
        { "startOffset": 3997, "endOffset": 4044, "count": 798 },
        { "startOffset": 4021, "endOffset": 4044, "count": 326 },
        { "startOffset": 4045, "endOffset": 4092, "count": 798 },
        { "startOffset": 4069, "endOffset": 4092, "count": 326 },
        { "startOffset": 4093, "endOffset": 4140, "count": 798 },
        { "startOffset": 4117, "endOffset": 4140, "count": 326 },
        { "startOffset": 4141, "endOffset": 4188, "count": 798 },
        { "startOffset": 4165, "endOffset": 4188, "count": 326 },
        { "startOffset": 4189, "endOffset": 4236, "count": 798 },
        { "startOffset": 4213, "endOffset": 4236, "count": 326 },
        { "startOffset": 4237, "endOffset": 4284, "count": 798 },
        { "startOffset": 4261, "endOffset": 4284, "count": 326 },
        { "startOffset": 4285, "endOffset": 4332, "count": 798 },
        { "startOffset": 4309, "endOffset": 4332, "count": 326 },
        { "startOffset": 4333, "endOffset": 4380, "count": 798 },
        { "startOffset": 4357, "endOffset": 4380, "count": 326 },
        { "startOffset": 4381, "endOffset": 4428, "count": 798 },
        { "startOffset": 4405, "endOffset": 4428, "count": 326 },
        { "startOffset": 4429, "endOffset": 4476, "count": 798 },
        { "startOffset": 4453, "endOffset": 4476, "count": 326 },
        { "startOffset": 4477, "endOffset": 4524, "count": 798 },
        { "startOffset": 4501, "endOffset": 4524, "count": 326 },
        { "startOffset": 4525, "endOffset": 4572, "count": 798 },
        { "startOffset": 4549, "endOffset": 4572, "count": 326 },
        { "startOffset": 4573, "endOffset": 4597, "count": 798 },
        { "startOffset": 4598, "endOffset": 4645, "count": 798 },
        { "startOffset": 4622, "endOffset": 4645, "count": 326 },
        { "startOffset": 4646, "endOffset": 4670, "count": 550 },
        { "startOffset": 4671, "endOffset": 4718, "count": 550 },
        { "startOffset": 4695, "endOffset": 4718, "count": 78 },
        { "startOffset": 4719, "endOffset": 4766, "count": 550 },
        { "startOffset": 4743, "endOffset": 4766, "count": 78 },
        { "startOffset": 4767, "endOffset": 4814, "count": 550 },
        { "startOffset": 4791, "endOffset": 4814, "count": 78 },
        { "startOffset": 4815, "endOffset": 4862, "count": 550 },
        { "startOffset": 4839, "endOffset": 4862, "count": 78 },
        { "startOffset": 4863, "endOffset": 4887, "count": 550 },
        { "startOffset": 4888, "endOffset": 4935, "count": 550 },
        { "startOffset": 4912, "endOffset": 4935, "count": 78 },
        { "startOffset": 4936, "endOffset": 4960, "count": 550 },
        { "startOffset": 4961, "endOffset": 5008, "count": 550 },
        { "startOffset": 4985, "endOffset": 5008, "count": 78 },
        { "startOffset": 5009, "endOffset": 5056, "count": 550 },
        { "startOffset": 5033, "endOffset": 5056, "count": 78 },
        { "startOffset": 5057, "endOffset": 5081, "count": 550 },
        { "startOffset": 5082, "endOffset": 5129, "count": 550 },
        { "startOffset": 5106, "endOffset": 5129, "count": 78 },
        { "startOffset": 5130, "endOffset": 5177, "count": 550 },
        { "startOffset": 5154, "endOffset": 5177, "count": 78 },
        { "startOffset": 5178, "endOffset": 5225, "count": 550 },
        { "startOffset": 5202, "endOffset": 5225, "count": 78 },
        { "startOffset": 5226, "endOffset": 5273, "count": 550 },
        { "startOffset": 5250, "endOffset": 5273, "count": 78 },
        { "startOffset": 5274, "endOffset": 5321, "count": 550 },
        { "startOffset": 5298, "endOffset": 5321, "count": 78 },
        { "startOffset": 5322, "endOffset": 5369, "count": 550 },
        { "startOffset": 5346, "endOffset": 5369, "count": 78 },
        { "startOffset": 5370, "endOffset": 5394, "count": 550 },
        { "startOffset": 5395, "endOffset": 5442, "count": 550 },
        { "startOffset": 5419, "endOffset": 5442, "count": 78 },
        { "startOffset": 5443, "endOffset": 5490, "count": 550 },
        { "startOffset": 5467, "endOffset": 5490, "count": 78 },
        { "startOffset": 5491, "endOffset": 5538, "count": 550 },
        { "startOffset": 5515, "endOffset": 5538, "count": 78 },
        { "startOffset": 5539, "endOffset": 5586, "count": 472 },
        { "startOffset": 5563, "endOffset": 5586, "count": 0 },
        { "startOffset": 5587, "endOffset": 5634, "count": 472 },
        { "startOffset": 5611, "endOffset": 5634, "count": 0 },
        { "startOffset": 5635, "endOffset": 5682, "count": 472 },
        { "startOffset": 5659, "endOffset": 5682, "count": 0 },
        { "startOffset": 5683, "endOffset": 5730, "count": 472 },
        { "startOffset": 5707, "endOffset": 5730, "count": 0 },
        { "startOffset": 5731, "endOffset": 5778, "count": 472 },
        { "startOffset": 5755, "endOffset": 5778, "count": 0 },
        { "startOffset": 5779, "endOffset": 5826, "count": 472 },
        { "startOffset": 5803, "endOffset": 5826, "count": 0 },
        { "startOffset": 5827, "endOffset": 5874, "count": 472 },
        { "startOffset": 5851, "endOffset": 5874, "count": 0 },
        { "startOffset": 5875, "endOffset": 5922, "count": 472 },
        { "startOffset": 5899, "endOffset": 5922, "count": 0 },
        { "startOffset": 5923, "endOffset": 5970, "count": 472 },
        { "startOffset": 5947, "endOffset": 5970, "count": 0 },
        { "startOffset": 5972, "endOffset": 5991, "count": 1229 },
        { "startOffset": 5991, "endOffset": 6004, "count": 472 }
      ],
      "isBlockCoverage": true
    }
  ]
}
